{"buses" : [
{"id":"101"},
{"id":"101c"},
{"id":"102"},
{"id":"103"},
{"id":"104"},
{"id":"105"},
{"id":"106"},
{"id":"107"},
{"id":"107c"},
{"id":"108"},
{"id":"109"},
{"id":"110"},
{"id":"110c"},
{"id":"111"},
{"id":"112"},
{"id":"113"},
{"id":"113e"},
{"id":"114"},
{"id":"115"},
{"id":"116"},
{"id":"117"},
{"id":"117c"},
{"id":"118"},
{"id":"119"},
{"id":"120"},
{"id":"121"},
{"id":"122"},
{"id":"125"},
{"id":"126"},
{"id":"201"},
{"id":"201c"},
{"id":"201e"},
{"id":"202c"},
{"id":"203"},
{"id":"203e"},
{"id":"204"},
{"id":"204e"},
{"id":"205"},
{"id":"205e"},
{"id":"206"},
{"id":"206e"},
{"id":"207c"},
{"id":"207e"},
{"id":"208"},
{"id":"208c"},
{"id":"209"},
{"id":"209e"},
{"id":"210"},
{"id":"211"},
{"id":"211c"},
{"id":"211e"},
{"id":"212"},
{"id":"213e"},
{"id":"214e"},
{"id":"216"},
{"id":"217e"},
{"id":"218e"},
{"id":"219e"},
{"id":"221e"},
{"id":"222e"},
{"id":"223"},
{"id":"224"},
{"id":"224c"},
{"id":"225"},
{"id":"226"},
{"id":"227"},
{"id":"228"},
{"id":"229"},
{"id":"230"},
{"id":"261e"},
{"id":"301"},
{"id":"301c"},
{"id":"301c2"},
{"id":"301e"},
{"id":"302"},
{"id":"302e"},
{"id":"303"},
{"id":"303e"},
{"id":"307"},
{"id":"307e"},
{"id":"308"},
{"id":"312e"},
{"id":"313e"},
{"id":"314"},
{"id":"315e"},
{"id":"321"},
{"id":"345"},
{"id":"348"},
{"id":"401"},
{"id":"401N"},
{"id":"402"},
{"id":"403"},
{"id":"404"},
{"id":"404c"},
{"id":"405"},
{"id":"405c"},
{"id":"406"},
{"id":"406c"},
{"id":"407"},
{"id":"408"},
{"id":"408e"},
{"id":"409"},
{"id":"410"},
{"id":"410e"},
{"id":"411"},
{"id":"412"},
{"id":"413c"},
{"id":"413v"},
{"id":"414e"},
{"id":"415e"},
{"id":"416e"},
{"id":"417e"},
{"id":"418"},
{"id":"419"},
{"id":"420e"},
{"id":"421"},
{"id":"422"},
{"id":"423"},
{"id":"424"},
{"id":"425"},
{"id":"426"},
{"id":"427"},
{"id":"428"},
{"id":"428c"},
{"id":"428e"},
{"id":"429"},
{"id":"429c"},
{"id":"430"},
{"id":"431c"},
{"id":"431v"},
{"id":"435"},
{"id":"501"},
{"id":"502"},
{"id":"502c"},
{"id":"503"},
{"id":"503c"},
{"id":"504"},
{"id":"505"},
{"id":"506"},
{"id":"506e"},
{"id":"506v"},
{"id":"507"},
{"id":"507c"},
{"id":"508"},
{"id":"509"},
{"id":"510"},
{"id":"510c"},
{"id":"511"},
{"id":"513"},
{"id":"514"},
{"id":"514c"},
{"id":"515N"},
{"id":"516"},
{"id":"517"},
{"id":"B01"},
{"id":"B02"},
{"id":"B03"},
{"id":"B04"},
{"id":"B04v"},
{"id":"B05"},
{"id":"B06"},
{"id":"B07"},
{"id":"B08"},
{"id":"B09"},
{"id":"B10"},
{"id":"B11"},
{"id":"B12"},
{"id":"B13"},
{"id":"B14"},
{"id":"B15"},
{"id":"B16"},
{"id":"B17"},
{"id":"B18"},
{"id":"B19"},
{"id":"B20"},
{"id":"B21"},
{"id":"B22"},
{"id":"B23"},
{"id":"B24"},
{"id":"B25"},
{"id":"B26"},
{"id":"B27"},
{"id":"B28"},
{"id":"C01"},
{"id":"C01c"},
{"id":"C02"},
{"id":"C02c"},
{"id":"C03"},
{"id":"C04"},
{"id":"C05"},
{"id":"C06"},
{"id":"C07"},
{"id":"C08"},
{"id":"C09"},
{"id":"C10e"},
{"id":"C11"},
{"id":"C11c"},
{"id":"C12"},
{"id":"C13"},
{"id":"C14"},
{"id":"C15"},
{"id":"C16"},
{"id":"C17"},
{"id":"C18"},
{"id":"C19"},
{"id":"C20"},
{"id":"C21N"},
{"id":"C22"},
{"id":"C23"},
{"id":"D01"},
{"id":"D02"},
{"id":"D03"},
{"id":"D05"},
{"id":"D06"},
{"id":"D07"},
{"id":"D07c"},
{"id":"D08"},
{"id":"D08c"},
{"id":"D09"},
{"id":"D10"},
{"id":"D11"},
{"id":"D12"},
{"id":"D13"},
{"id":"D14"},
{"id":"D15"},
{"id":"D16"},
{"id":"D17"},
{"id":"D18"},
{"id":"E01"},
{"id":"E02"},
{"id":"E03"},
{"id":"E03v"},
{"id":"E04"},
{"id":"E05"},
{"id":"E06"},
{"id":"E07"},
{"id":"E08"},
{"id":"E09"},
{"id":"E10"},
{"id":"E11"},
{"id":"E12"},
{"id":"E13"},
{"id":"E14"},
{"id":"E15"},
{"id":"E15c"},
{"id":"E16"},
{"id":"E17"},
{"id":"E18"},
{"id":"F01"},
{"id":"F01c"},
{"id":"F02"},
{"id":"F03"},
{"id":"F03c"},
{"id":"F05"},
{"id":"F06"},
{"id":"F07"},
{"id":"F08"},
{"id":"F09"},
{"id":"F10"},
{"id":"F11"},
{"id":"F12"},
{"id":"F12c"},
{"id":"F13"},
{"id":"F13c"},
{"id":"F14"},
{"id":"F15"},
{"id":"F16"},
{"id":"F17"},
{"id":"F18"},
{"id":"F19"},
{"id":"F20"},
{"id":"F21"},
{"id":"F22"},
{"id":"F23"},
{"id":"F24"},
{"id":"F25"},
{"id":"F25e"},
{"id":"F26"},
{"id":"G01"},
{"id":"G01c"},
{"id":"G02"},
{"id":"G03"},
{"id":"G04"},
{"id":"G05"},
{"id":"G07"},
{"id":"G08"},
{"id":"G08v"},
{"id":"G09"},
{"id":"G11"},
{"id":"G12"},
{"id":"G13"},
{"id":"G14"},
{"id":"G15"},
{"id":"G16"},
{"id":"G18"},
{"id":"G22"},
{"id":"H01"},
{"id":"H02"},
{"id":"H03"},
{"id":"H04"},
{"id":"H05"},
{"id":"H05c"},
{"id":"H06"},
{"id":"H07"},
{"id":"H08"},
{"id":"H09"},
{"id":"H12"},
{"id":"H13"},
{"id":"H14"},
{"id":"I01"},
{"id":"I02"},
{"id":"I03"},
{"id":"I03c"},
{"id":"I04"},
{"id":"I04c"},
{"id":"I04e"},
{"id":"I05"},
{"id":"I07"},
{"id":"I08"},
{"id":"I08c"},
{"id":"I09"},
{"id":"I09c"},
{"id":"I09e"},
{"id":"I09v"},
{"id":"I10"},
{"id":"I11"},
{"id":"I12"},
{"id":"I13"},
{"id":"I14"},
{"id":"I15"},
{"id":"I16"},
{"id":"I17"},
{"id":"I18"},
{"id":"I20"},
{"id":"I21"},
{"id":"I22"},
{"id":"I23"},
{"id":"I24"},
{"id":"J01"},
{"id":"J01c"},
{"id":"J02"},
{"id":"J03"},
{"id":"J04"},
{"id":"J04c"},
{"id":"J05"},
{"id":"J06"},
{"id":"J07"},
{"id":"J07c"},
{"id":"J07e"},
{"id":"J08"},
{"id":"J08c"},
{"id":"J10"},
{"id":"J11"},
{"id":"J12"},
{"id":"J13"},
{"id":"J13c"},
{"id":"J14c"},
{"id":"J15c"},
{"id":"J16"},
{"id":"J17"},
{"id":"J18"},
{"id":"J18c"},
{"id":"J19"},
{"id":"J19c"}
]}